papero/__init__.py
papero/codec.py
papero/converter.py
papero/iobuf.py
papero/property.py
papero-0.2.7.dist-info/LICENSE
papero-0.2.7.dist-info/METADATA
papero-0.2.7.dist-info/WHEEL
papero-0.2.7.dist-info/top_level.txt
papero-0.2.7.dist-info/RECORD
